petrinex/__init__.py
petrinex/client.py
petrinex-1.1.1.dist-info/licenses/LICENSE
petrinex-1.1.1.dist-info/METADATA
petrinex-1.1.1.dist-info/WHEEL
petrinex-1.1.1.dist-info/top_level.txt
petrinex-1.1.1.dist-info/RECORD
