Metadata-Version: 2.4
Name: petrinex
Version: 1.1.1
Summary: Load Alberta Petrinex data (Volumetrics, NGL) into Spark/pandas DataFrames
Home-page: https://github.com/guanjieshen/petrinex-python-api
Author: Guanjie Shen
License: MIT
Project-URL: Homepage, https://github.com/guanjieshen/petrinex-python-api
Project-URL: Documentation, https://github.com/guanjieshen/petrinex-python-api#readme
Project-URL: Repository, https://github.com/guanjieshen/petrinex-python-api
Project-URL: Bug Reports, https://github.com/guanjieshen/petrinex-python-api/issues
Keywords: petrinex,alberta,oil,gas,volumetrics,ngl,spark,databricks,unity-catalog,energy-data
Classifier: Development Status :: 4 - Beta
Classifier: Intended Audience :: Developers
Classifier: Intended Audience :: Science/Research
Classifier: License :: OSI Approved :: MIT License
Classifier: Programming Language :: Python :: 3
Classifier: Programming Language :: Python :: 3.8
Classifier: Programming Language :: Python :: 3.9
Classifier: Programming Language :: Python :: 3.10
Classifier: Programming Language :: Python :: 3.11
Classifier: Programming Language :: Python :: 3.12
Classifier: Topic :: Scientific/Engineering
Classifier: Topic :: Software Development :: Libraries :: Python Modules
Requires-Python: >=3.8
License-File: LICENSE
Requires-Dist: beautifulsoup4>=4.9.0
Requires-Dist: lxml>=4.6.0
Requires-Dist: pandas>=1.2.0
Requires-Dist: requests>=2.25.0
Requires-Dist: pyspark>=3.0.0
Provides-Extra: dev
Requires-Dist: pytest>=6.0; extra == "dev"
Requires-Dist: pytest-cov>=2.0; extra == "dev"
Dynamic: home-page
Dynamic: license-file
Dynamic: requires-python
